{
  "required": true,
  "minVersion": "0.8",
  "package": "btw.community.denovo.mixins",
  "compatibilityLevel": "JAVA_8",
  "mixins": [
    "BlockLeavesMixin",
    "CampfireBlockMixin",
    "DeadBushBlockMixin",
    "EntityLivingMixin",
    "FarmlandBlockBaseMixin",
    "FishingRodBaitingRecipeMixin",
    "GrassBlockMixin",
    "HardcoreSpawnUtilsMixin",
    "ItemCoalMixin",
    "OreBlockStagedMixin",
    "PlanterBlockSoilMixin",
    "SaplingBlockMixin",
    "ShaftItemMixin",
    "SlimeEntityMixin",
    "StoneBlockMixin",
    "ItemMixin"
  ],
  "client": [
  ],
  "injectors": {
    "defaultRequire": 1
  }
}
